AMLBID/__init__.py
AMLBID/loader.py
AMLBID/Explainer/AMLBID_Dashboard.py
AMLBID/Explainer/AMLBID_Explainer.py
AMLBID/Explainer/__init__.py
AMLBID/Explainer/cli.py
AMLBID/Explainer/custom.py
AMLBID/Explainer/dashboard_methods.py
AMLBID/Explainer/dashboard_tabs.py
AMLBID/Explainer/dashboardss.py
AMLBID/Explainer/datasets.py
AMLBID/Explainer/explainer_methods.py
AMLBID/Explainer/explainer_plots.py
AMLBID/Explainer/explainerss.py
AMLBID/Explainer/make_callables.py
AMLBID/Explainer/assets/ANOVA_FINAL.csv
AMLBID/Explainer/assets/ModelsDescription.pkl
AMLBID/Explainer/assets/bootstrap.css
AMLBID/Explainer/assets/bootstrap.min.css
AMLBID/Explainer/assets/favicon.ico
AMLBID/Explainer/assets/ffavicon.ico
AMLBID/Explainer/assets/framework.png
AMLBID/Explainer/dashboard_components/ConfGenerator.py
AMLBID/Explainer/dashboard_components/__init__.py
AMLBID/Explainer/dashboard_components/classifier_components.py
AMLBID/Explainer/dashboard_components/composites.py
AMLBID/Explainer/dashboard_components/connectors.py
AMLBID/Explainer/dashboard_components/decisiontree_components.py
AMLBID/Explainer/dashboard_components/overview_components.py
AMLBID/Explainer/dashboard_components/regression_components.py
AMLBID/Explainer/dashboard_components/shap_components.py
AMLBID/Recommender/AMLBID_Recommender.py
AMLBID/Recommender/__init__.py
AMLBID/Recommender/assets/__init__.py
AMLBID/Recommender/assets/MetafeatureExtraction/__init__.py
AMLBID/Recommender/assets/MetafeatureExtraction/metafeatures.py
AMLBID/Recommender/builtins/KnowledgeBase/KB_Acc.csv
AMLBID/Recommender/builtins/KnowledgeBase/MF_FOR_ANOVA.csv
AMLBID/Recommender/builtins/KnowledgeBase/metafeatures.csv
AMLBID/Recommender/recommender_components/MetafeaturesExtractor.py
AMLBID/Recommender/recommender_components/__init__.py
AMLBID/Recommender/recommender_components/loader.py
AMLBID-0.3.dist-info/LICENSE
AMLBID-0.3.dist-info/METADATA
AMLBID-0.3.dist-info/WHEEL
AMLBID-0.3.dist-info/top_level.txt
AMLBID-0.3.dist-info/RECORD
