Metadata-Version: 2.1
Name: AMLBID
Version: 0.3
Summary: Transparent and Auto-explainable AutoML
Home-page: https://github.com/LeMGarouani/AMLBID
Author: Moncef GAROUANI
Author-email: mgarouani@gmail.com
License: MIT
Project-URL: Github page, https://github.com/LeMGarouani/AMLBID
Project-URL: Documentation, https://github.com/LeMGarouani/AMLBID
Keywords: machine learning,Automated machine learning,explainability
Platform: UNKNOWN
Classifier: Development Status :: 3 - Alpha
Classifier: Environment :: Web Environment
Classifier: Framework :: Dash
Classifier: Framework :: Flask
Classifier: Topic :: Scientific/Engineering :: Artificial Intelligence
Requires-Python: >=3.6
License-File: LICENSE
Requires-Dist: dash (>=1.20)
Requires-Dist: dash-bootstrap-components
Requires-Dist: jupyter-dash
Requires-Dist: dash-auth
Requires-Dist: dtreeviz (>=1.3)
Requires-Dist: numpy
Requires-Dist: pandas (>=1.1)
Requires-Dist: scikit-learn
Requires-Dist: shap (>=0.37)
Requires-Dist: joblib
Requires-Dist: oyaml
Requires-Dist: click
Requires-Dist: waitress
Requires-Dist: flask-simplelogin
Requires-Dist: xgboost
Requires-Dist: termcolor
Requires-Dist: pdpbox
Requires-Dist: shortuuid
